{
  "product_id": "1729520223359703061",
  "scraped_at": "2026-01-20T22:01:36.971502",
  "product_info": {
    "product_name": "(Halbpreis begrenzt)MAWIROM Großes Akku-Gebläse, kompatibel mit Makita 18V/20V-Akkus Leichter leistungsstarker Blower Garten, 18V elektrischer Blattbläser Staub, Schnee Müll, Hof, Arbeit rund um das Haus",
    "shop_owner": "LWtoolbox_Germany",
    "total_sales": 29,
    "total_sales_revenue": "€ 440.10($ 512.34)",
    "product_rating": null,
    "category": null
  },
  "sales_data": {
    "date_range": "7day",
    "sales_count": 0,
    "sales_revenue": "$ 0.00",
    "related_videos": null,
    "related_creators": null,
    "conversion_rate": "0.00%",
    "click_through_rate": null
  },
  "video_analysis": {
    "带货视频数": 13,
    "带货视频达人数": 6,
    "带货视频销量": 0,
    "带货视频销售额": "$ 0.00",
    "广告成交金额": "$ 0.00",
    "广告成交占比": "-"
  },
  "top_videos": [
    {
      "rank": 1,
      "title": "ADLuft Gebläse von MAWIRON mit 2 Batterien 18V 5.5ah mega Preis gibt euch #tiktokshop #tiktokdeutschland #deutsch #fürdich #gebläse 发现时间：2026.01.12 05:57更新时间：2026.01.12 05:57时长：00:02:20跳转至 TikTok",
      "creator_username": "mrbooster82",
      "creator_followers": "1.13万",
      "publish_date": "2026-01-11 14:26",
      "estimated_sales": 0,
      "estimated_revenue": "€ 0.00($ 0.00)",
      "total_views": "280",
      "video_url": "https://www.tiktok.com/@mrbooster82/video/7594071722588933408?is_copy_url=1&is_from_webapp=v1",
      "video_id": null,
      "local_path": "ref_video/video_1_mrbooster82.mp4"
    },
    {
      "rank": 2,
      "title": "ADDieser puster ist mega leicht von MAWIRON gibt euch #tiktokshop #deutsch #tiktokdeutschland #fürdich #gebläse 发现时间：2026.01.15 09:59更新时间：2026.01.15 09:59时长：00:01:23跳转至 TikTok",
      "creator_username": "mrbooster82",
      "creator_followers": "1.13万",
      "publish_date": "2026-01-14 12:01",
      "estimated_sales": 0,
      "estimated_revenue": "€ 0.00($ 0.00)",
      "total_views": "305",
      "video_url": "https://www.tiktok.com/@mrbooster82/video/7595163139130330400?is_copy_url=1&is_from_webapp=v1",
      "video_id": null,
      "local_path": "ref_video/video_2_mrbooster82.mp4"
    },
    {
      "rank": 3,
      "title": "AD#tiktokshop #gebläse #fürdich #tiktokdeutschland #deutsch 发现时间：2026.01.16 08:25更新时间：2026.01.16 08:25时长：00:01:08跳转至 TikTok",
      "creator_username": "mrbooster82",
      "creator_followers": "1.13万",
      "publish_date": "2026-01-15 11:12",
      "estimated_sales": 0,
      "estimated_revenue": "€ 0.00($ 0.00)",
      "total_views": "621",
      "video_url": "https://www.tiktok.com/@mrbooster82/video/7595529239538011425?is_copy_url=1&is_from_webapp=v1",
      "video_id": null,
      "local_path": "ref_video/video_3_mrbooster82.mp4"
    },
    {
      "rank": 4,
      "title": "ADLuft Gebläse von MAWIRON Mit 2 akku 18v 5.5ah gibt euch #tiktokshop #deals #tiktokdeutschland #deutsch #fürdich 发现时间：2026.01.13 11:02更新时间：2026.01.15 03:41时长：00:00:35跳转至 TikTok",
      "creator_username": "mrbooster82",
      "creator_followers": "1.13万",
      "publish_date": "2026-01-12 18:00",
      "estimated_sales": 0,
      "estimated_revenue": "€ 0.00($ 0.00)",
      "total_views": "797",
      "video_url": "https://www.tiktok.com/@mrbooster82/video/7594432747834199328?is_copy_url=1&is_from_webapp=v1",
      "video_id": null,
      "local_path": "ref_video/video_4_mrbooster82.mp4"
    },
    {
      "rank": 5,
      "title": "AD无标题发现时间：2026.01.16 05:22更新时间：2026.01.19 07:17时长：00:02:22跳转至 TikTok",
      "creator_username": "sauan.alexandru",
      "creator_followers": "20.22万",
      "publish_date": "2026-01-15 21:06",
      "estimated_sales": 0,
      "estimated_revenue": "€ 0.00($ 0.00)",
      "total_views": "737",
      "video_url": "https://www.tiktok.com/@sauan.alexandru/video/7595682119108775171?is_copy_url=1&is_from_webapp=v1",
      "video_id": null,
      "local_path": "ref_video/video_5_sauan.alexandru.mp4"
    }
  ]
}